iyg_tools/__init__.py
iyg_tools/tckn.py
iyg_tools-1.0.3.dist-info/LICENSE
iyg_tools-1.0.3.dist-info/METADATA
iyg_tools-1.0.3.dist-info/WHEEL
iyg_tools-1.0.3.dist-info/top_level.txt
iyg_tools-1.0.3.dist-info/RECORD
