Metadata-Version: 2.1
Name: iyg_tools
Version: 1.0.3
Home-page: https://github.com/ilkeryolundagerek/iyg_tools
Author: İlker Turan
Author-email: ilkerturan@outlook.com
Classifier: Programming Language :: Python :: 3
Classifier: License :: OSI Approved :: MIT License
Classifier: Operating System :: OS Independent
Requires-Python: >=3.6
License-File: LICENSE
